facelib/__init__.py
facelib/__main__.py
facelib/_utils/__init__.py
facelib/_utils/face_recognition.py
facelib/_utils/helper.py
facelib/_utils/links_to_models.ini
facelib/_utils/settings.ini
facelib/_utils/templates.ini
facelib/dev/__init__.py
facelib/dev/image.py
facelib/dev/layer.py
facelib/dev/model.py
facelib/dev/loss/__init__.py
facelib/dev/loss/euclidean_distance.py
facelib/dev/loss/functions.py
facelib/dev/loss/margin.py
facelib/facerec/__init__.py
facelib/facerec/pipeline.py
facelib/facerec/face_detection/__init__.py
facelib/facerec/face_detection/cascade.py
facelib/facerec/face_detection/ssd.py
facelib/facerec/feature_extraction/__init__.py
facelib/facerec/feature_extraction/feature_extractor.py
facelib/facerec/landmark_detection/__init__.py
facelib/facerec/landmark_detection/landmark_detector.py
facelib-1.2.1.dist-info/LICENSE
facelib-1.2.1.dist-info/METADATA
facelib-1.2.1.dist-info/WHEEL
facelib-1.2.1.dist-info/top_level.txt
facelib-1.2.1.dist-info/RECORD
