Metadata-Version: 2.1
Name: facelib
Version: 1.2.1
Summary: Face Recognition (train/test/deploy)(tensorflow/tflite/keras/edgetpu)
Home-page: https://github.com/kutayyildiz/facelib
Author: Kutay YILDIZ
Author-email: kkutayyildiz@gmail.com
License: UNKNOWN
Project-URL: Source, https://github.com/kutayyildiz/facelib
Keywords: face,recognition,detection,tensorflow,lite,keras,loss,layer,edgetpu
Platform: UNKNOWN
Classifier: Development Status :: 2 - Pre-Alpha
Classifier: Intended Audience :: Developers
Classifier: Intended Audience :: Science/Research
Classifier: Intended Audience :: Information Technology
Classifier: Topic :: Software Development :: Build Tools
Classifier: License :: OSI Approved :: MIT License
Classifier: Programming Language :: Python :: 3.5
Classifier: Programming Language :: Python :: 3.6
Classifier: Programming Language :: Python :: 3.7
Requires-Python: >=3.5, <3.8
Requires-Dist: joblib
Requires-Dist: opencv-python
Requires-Dist: numpy
Requires-Dist: scikit-image
Requires-Dist: scikit-learn
Provides-Extra: dev
Requires-Dist: tensorflow ; extra == 'dev'
